sz_testing_1/__init__.py
sz_testing_1/test_me.py
sz_testing_1-0.0.2.dist-info/METADATA
sz_testing_1-0.0.2.dist-info/WHEEL
sz_testing_1-0.0.2.dist-info/top_level.txt
sz_testing_1-0.0.2.dist-info/RECORD
