Metadata-Version: 2.1
Name: sz-testing-1
Version: 0.0.2
Summary: Print add function for test
Home-page: UNKNOWN
Author: Emeric Szaboky
Author-email: <emeric.szaboky@rakuten.com>
License: UNKNOWN
Keywords: python,first package
Platform: UNKNOWN
Classifier: Development Status :: 3 - Alpha
Classifier: Intended Audience :: Education
Classifier: Programming Language :: Python :: 2
Classifier: Programming Language :: Python :: 3
Classifier: Operating System :: MacOS :: MacOS X
Classifier: Operating System :: Microsoft :: Windows
